rocket_firstpackage/__init__.py
rocket_firstpackage/rocket_firstpackage.py
rocket_firstpackage-0.1.0.dist-info/LICENSE.txt
rocket_firstpackage-0.1.0.dist-info/METADATA
rocket_firstpackage-0.1.0.dist-info/WHEEL
rocket_firstpackage-0.1.0.dist-info/top_level.txt
rocket_firstpackage-0.1.0.dist-info/RECORD
